genetic_algorithms_personal/__init__.py
genetic_algorithms_personal/genetic_algorithm.py
genetic_algorithms_personal/pygame_visualization.py
genetic_algorithms_personal/utilities.py
genetic_algorithms_personal-0.2.0.dist-info/METADATA
genetic_algorithms_personal-0.2.0.dist-info/WHEEL
genetic_algorithms_personal-0.2.0.dist-info/top_level.txt
genetic_algorithms_personal-0.2.0.dist-info/RECORD
