Metadata-Version: 2.1
Name: genetic_algorithms_personal
Version: 0.2.0
Summary: A custom genetic algorithm package with Pygame visualization.
Author: NinjaNick
Author-email: nicholas.starbuck@mnstu.catholic.edu.au
Classifier: Programming Language :: Python :: 3
Classifier: License :: OSI Approved :: MIT License
Classifier: Operating System :: OS Independent
Requires-Python: >=3.6
Requires-Dist: pygame
